CHANGES.rst
DESCRIPTION.rst
LICENSE
MANIFEST.in
README.md
setup.py
src/wai.annotations.opex.egg-info/PKG-INFO
src/wai.annotations.opex.egg-info/SOURCES.txt
src/wai.annotations.opex.egg-info/dependency_links.txt
src/wai.annotations.opex.egg-info/entry_points.txt
src/wai.annotations.opex.egg-info/namespace_packages.txt
src/wai.annotations.opex.egg-info/requires.txt
src/wai.annotations.opex.egg-info/top_level.txt
src/wai/annotations/opex/__init__.py
src/wai/annotations/opex/od/__init__.py
src/wai/annotations/opex/od/_format.py
src/wai/annotations/opex/od/component/_FromOPEXOD.py
src/wai/annotations/opex/od/component/_OPEXODReader.py
src/wai/annotations/opex/od/component/_OPEXODWriter.py
src/wai/annotations/opex/od/component/_ToOPEXOD.py
src/wai/annotations/opex/od/component/__init__.py
src/wai/annotations/opex/od/specifier/_OPEXODInputFormatSpecifier.py
src/wai/annotations/opex/od/specifier/_OPEXODOutputFormatSpecifier.py
src/wai/annotations/opex/od/specifier/__init__.py